[
    {
        "application_no": "2645836225",
        "name": "ATUL CHOKHANDRE",
        "application_date": "04-07-2025",
        "date_of_birth": "01-06-1975",
        "blood_group": "Unknown",
        "father_name": "PAIKAM CHOKHANDRE",
        "applicant_gender": "Male",
        "dl_number": "MH34 20120007111",
        "dl_covs": "MCWG",
        "nt_validity": "23-05-2012 to 31-05-2025",
        "tr_validity": "",
        "learning_no": "",
        "mobile_no": "",
        "learning_created_date": "",
        "learning_expired_date": "",
        "licence_type": "",
        "appointment_date": "",
        "rto_office": "",
        "attendance": "",
        "result": "",
        "total": ""
    },
    {
        "application_no": "2658504225",
        "name": "AYUSH NITESH NAGARKAR",
        "application_date": "05-07-2025",
        "date_of_birth": "23-06-2007",
        "blood_group": "Unknown",
        "father_name": "NITESH BHAURAV NAGARKAR",
        "applicant_gender": "Male",
        "dl_number": "",
        "dl_covs": "",
        "nt_validity": "",
        "tr_validity": "",
        "learning_no": "",
        "mobile_no": "",
        "learning_created_date": "",
        "learning_expired_date": "",
        "licence_type": "",
        "appointment_date": "",
        "rto_office": "",
        "attendance": "",
        "result": "",
        "total": ""
    },
    {
        "application_no": "1770588225",
        "name": "UGAM SUDHIR BURAD",
        "application_date": "07-05-2025",
        "date_of_birth": "05-05-2007",
        "blood_group": "Unknown",
        "father_name": "SUDHIR BURAD",
        "applicant_gender": "Male",
        "dl_number": "",
        "dl_covs": "",
        "nt_validity": "",
        "tr_validity": "",
        "learning_no": "",
        "mobile_no": "",
        "learning_created_date": "",
        "learning_expired_date": "",
        "licence_type": "",
        "appointment_date": "",
        "rto_office": "",
        "attendance": "",
        "result": "",
        "total": ""
    },
    {
        "application_no": "1770588225",
        "name": "UGAM SUDHIR BURAD",
        "application_date": "07-05-2025",
        "date_of_birth": "05-05-2007",
        "blood_group": "Unknown",
        "father_name": "SUDHIR BURAD",
        "applicant_gender": "Male",
        "dl_number": "",
        "dl_covs": "",
        "nt_validity": "",
        "tr_validity": "",
        "learning_no": "",
        "mobile_no": "",
        "learning_created_date": "",
        "learning_expired_date": "",
        "licence_type": "",
        "appointment_date": "",
        "rto_office": "",
        "attendance": "",
        "result": "",
        "total": ""
    },
    {
        "application_no": "2645836225",
        "name": "ATUL CHOKHANDRE",
        "application_date": "04-07-2025",
        "date_of_birth": "01-06-1975",
        "blood_group": "Unknown",
        "father_name": "PAIKAM CHOKHANDRE",
        "applicant_gender": "Male",
        "dl_number": "MH34 20120007111",
        "dl_covs": "MCWG",
        "nt_validity": "23-05-2012 to 31-05-2025",
        "tr_validity": "",
        "learning_no": "",
        "mobile_no": "",
        "learning_created_date": "",
        "learning_expired_date": "",
        "licence_type": "",
        "appointment_date": "",
        "rto_office": "",
        "attendance": "",
        "result": "",
        "total": ""
    },
    {
        "application_no": "2645836225",
        "name": "ATUL CHOKHANDRE",
        "application_date": "04-07-2025",
        "date_of_birth": "01-06-1975",
        "blood_group": "Unknown",
        "father_name": "PAIKAM CHOKHANDRE",
        "applicant_gender": "Male",
        "dl_number": "MH34 20120007111",
        "dl_covs": "MCWG",
        "nt_validity": "23-05-2012 to 31-05-2025",
        "tr_validity": "",
        "learning_no": "",
        "mobile_no": "9689123576",
        "learning_created_date": "",
        "learning_expired_date": "",
        "licence_type": "dl",
        "appointment_date": "",
        "rto_office": "",
        "attendance": "",
        "result": "",
        "total": ""
    },
    {
        "application_no": "2645836225",
        "name": "ATUL CHOKHANDRE",
        "application_date": "04-07-2025",
        "date_of_birth": "01-06-1975",
        "blood_group": "Unknown",
        "father_name": "PAIKAM CHOKHANDRE",
        "applicant_gender": "Male",
        "dl_number": "MH34 20120007111",
        "dl_covs": "MCWG",
        "nt_validity": "23-05-2012 to 31-05-2025",
        "tr_validity": "",
        "learning_no": "",
        "mobile_no": "",
        "learning_created_date": "",
        "learning_expired_date": "",
        "licence_type": "renewal",
        "appointment_date": "",
        "rto_office": "",
        "attendance": "",
        "result": "",
        "total": ""
    },
    {
        "application_no": "2645836225",
        "name": "ATUL CHOKHANDRE",
        "application_date": "04-07-2025",
        "date_of_birth": "01-06-1975",
        "blood_group": "Unknown",
        "father_name": "PAIKAM CHOKHANDRE",
        "applicant_gender": "Male",
        "dl_number": "MH34 20120007111",
        "dl_covs": "MCWG",
        "nt_validity": "23-05-2012 to 31-05-2025",
        "tr_validity": "",
        "learning_no": "",
        "mobile_no": "",
        "learning_created_date": "",
        "learning_expired_date": "",
        "licence_type": "ll",
        "appointment_date": "",
        "rto_office": "",
        "attendance": "",
        "result": "",
        "total": ""
    },
    {
        "application_no": "2645836225",
        "name": "ATUL CHOKHANDRE",
        "application_date": "04-07-2025",
        "date_of_birth": "01-06-1975",
        "blood_group": "Unknown",
        "father_name": "PAIKAM CHOKHANDRE",
        "applicant_gender": "Male",
        "dl_number": "MH34 20120007111",
        "dl_covs": "MCWG",
        "nt_validity": "23-05-2012 to 31-05-2025",
        "tr_validity": "",
        "learning_no": "",
        "mobile_no": "",
        "learning_created_date": "",
        "learning_expired_date": "",
        "licence_type": "",
        "appointment_date": "",
        "rto_office": "",
        "attendance": "",
        "result": "",
        "total": ""
    }
]